webschaber/__init__.py
webschaber-1.0.dist-info/DESCRIPTION.rst
webschaber-1.0.dist-info/METADATA
webschaber-1.0.dist-info/RECORD
webschaber-1.0.dist-info/WHEEL
webschaber-1.0.dist-info/metadata.json
webschaber-1.0.dist-info/top_level.txt
