Metadata-Version: 2.0
Name: webschaber
Version: 1.0
Summary: The WebSchaber is python3 script which extracts the text and images content on search engine `bing.com`
Home-page: https://www.github.com/anubhav4sachan/WebSchaber
Author: Anubhav Sachan
Author-email: anubhav4sachan@gmail.com
License: UNKNOWN
Platform: UNKNOWN
